btrfs_backup/__init__.py
btrfs_backup/__main__.py
btrfs_backup/util.py
btrfs_backup/endpoint/__init__.py
btrfs_backup/endpoint/common.py
btrfs_backup/endpoint/local.py
btrfs_backup/endpoint/shell.py
btrfs_backup/endpoint/ssh.py
btrfs_backup-0.3.1.dist-info/DESCRIPTION.rst
btrfs_backup-0.3.1.dist-info/METADATA
btrfs_backup-0.3.1.dist-info/RECORD
btrfs_backup-0.3.1.dist-info/WHEEL
btrfs_backup-0.3.1.dist-info/entry_points.txt
btrfs_backup-0.3.1.dist-info/metadata.json
btrfs_backup-0.3.1.dist-info/top_level.txt
