Metadata-Version: 2.0
Name: btrfs-backup
Version: 0.3.1
Summary: Intelligent, feature-rich backups for btrfs
Home-page: https://github.com/efficiosoft/btrfs-backup
Author: Robert Schindler
Author-email: r.schindler@efficiosoft.com
License: MIT
Platform: UNKNOWN
